travelplanner/__init__.py
travelplanner/myenv/.gitignore
travelplanner/myenv/pyvenv.cfg
travelplanner/myenv/Lib/site-packages/build/__init__.py
travelplanner/myenv/Lib/site-packages/build/__main__.py
travelplanner/myenv/Lib/site-packages/build/_builder.py
travelplanner/myenv/Lib/site-packages/build/_ctx.py
travelplanner/myenv/Lib/site-packages/build/_exceptions.py
travelplanner/myenv/Lib/site-packages/build/_types.py
travelplanner/myenv/Lib/site-packages/build/_util.py
travelplanner/myenv/Lib/site-packages/build/env.py
travelplanner/myenv/Lib/site-packages/build/py.typed
travelplanner/myenv/Lib/site-packages/build/util.py
travelplanner/myenv/Lib/site-packages/build/_compat/__init__.py
travelplanner/myenv/Lib/site-packages/build/_compat/importlib.py
travelplanner/myenv/Lib/site-packages/build/_compat/tarfile.py
travelplanner/myenv/Lib/site-packages/build/_compat/tomllib.py
travelplanner/myenv/Lib/site-packages/build-1.2.2.post1.dist-info/INSTALLER
travelplanner/myenv/Lib/site-packages/build-1.2.2.post1.dist-info/LICENSE
travelplanner/myenv/Lib/site-packages/build-1.2.2.post1.dist-info/METADATA
travelplanner/myenv/Lib/site-packages/build-1.2.2.post1.dist-info/RECORD
travelplanner/myenv/Lib/site-packages/build-1.2.2.post1.dist-info/REQUESTED
travelplanner/myenv/Lib/site-packages/build-1.2.2.post1.dist-info/WHEEL
travelplanner/myenv/Lib/site-packages/build-1.2.2.post1.dist-info/entry_points.txt
travelplanner/myenv/Lib/site-packages/certifi/__init__.py
travelplanner/myenv/Lib/site-packages/certifi/__main__.py
travelplanner/myenv/Lib/site-packages/certifi/cacert.pem
travelplanner/myenv/Lib/site-packages/certifi/core.py
travelplanner/myenv/Lib/site-packages/certifi/py.typed
travelplanner/myenv/Lib/site-packages/certifi-2024.12.14.dist-info/INSTALLER
travelplanner/myenv/Lib/site-packages/certifi-2024.12.14.dist-info/LICENSE
travelplanner/myenv/Lib/site-packages/certifi-2024.12.14.dist-info/METADATA
travelplanner/myenv/Lib/site-packages/certifi-2024.12.14.dist-info/RECORD
travelplanner/myenv/Lib/site-packages/certifi-2024.12.14.dist-info/WHEEL
travelplanner/myenv/Lib/site-packages/certifi-2024.12.14.dist-info/top_level.txt
travelplanner/myenv/Lib/site-packages/charset_normalizer/__init__.py
travelplanner/myenv/Lib/site-packages/charset_normalizer/__main__.py
travelplanner/myenv/Lib/site-packages/charset_normalizer/api.py
travelplanner/myenv/Lib/site-packages/charset_normalizer/cd.py
travelplanner/myenv/Lib/site-packages/charset_normalizer/constant.py
travelplanner/myenv/Lib/site-packages/charset_normalizer/legacy.py
travelplanner/myenv/Lib/site-packages/charset_normalizer/md.py
travelplanner/myenv/Lib/site-packages/charset_normalizer/models.py
travelplanner/myenv/Lib/site-packages/charset_normalizer/py.typed
travelplanner/myenv/Lib/site-packages/charset_normalizer/utils.py
travelplanner/myenv/Lib/site-packages/charset_normalizer/version.py
travelplanner/myenv/Lib/site-packages/charset_normalizer/cli/__init__.py
travelplanner/myenv/Lib/site-packages/charset_normalizer-3.4.1.dist-info/INSTALLER
travelplanner/myenv/Lib/site-packages/charset_normalizer-3.4.1.dist-info/LICENSE
travelplanner/myenv/Lib/site-packages/charset_normalizer-3.4.1.dist-info/METADATA
travelplanner/myenv/Lib/site-packages/charset_normalizer-3.4.1.dist-info/RECORD
travelplanner/myenv/Lib/site-packages/charset_normalizer-3.4.1.dist-info/WHEEL
travelplanner/myenv/Lib/site-packages/charset_normalizer-3.4.1.dist-info/entry_points.txt
travelplanner/myenv/Lib/site-packages/charset_normalizer-3.4.1.dist-info/top_level.txt
travelplanner/myenv/Lib/site-packages/colorama-0.4.6.dist-info/INSTALLER
travelplanner/myenv/Lib/site-packages/colorama-0.4.6.dist-info/METADATA
travelplanner/myenv/Lib/site-packages/colorama-0.4.6.dist-info/RECORD
travelplanner/myenv/Lib/site-packages/colorama-0.4.6.dist-info/WHEEL
travelplanner/myenv/Lib/site-packages/colorama-0.4.6.dist-info/licenses/LICENSE.txt
travelplanner/myenv/Lib/site-packages/docutils-0.21.2.dist-info/COPYING.txt
travelplanner/myenv/Lib/site-packages/docutils-0.21.2.dist-info/INSTALLER
travelplanner/myenv/Lib/site-packages/docutils-0.21.2.dist-info/METADATA
travelplanner/myenv/Lib/site-packages/docutils-0.21.2.dist-info/RECORD
travelplanner/myenv/Lib/site-packages/docutils-0.21.2.dist-info/WHEEL
travelplanner/myenv/Lib/site-packages/docutils-0.21.2.dist-info/entry_points.txt
travelplanner/myenv/Lib/site-packages/id-1.5.0.dist-info/INSTALLER
travelplanner/myenv/Lib/site-packages/id-1.5.0.dist-info/LICENSE
travelplanner/myenv/Lib/site-packages/id-1.5.0.dist-info/METADATA
travelplanner/myenv/Lib/site-packages/id-1.5.0.dist-info/RECORD
travelplanner/myenv/Lib/site-packages/id-1.5.0.dist-info/WHEEL
travelplanner/myenv/Lib/site-packages/id-1.5.0.dist-info/entry_points.txt
travelplanner/myenv/Lib/site-packages/idna-3.10.dist-info/INSTALLER
travelplanner/myenv/Lib/site-packages/idna-3.10.dist-info/LICENSE.md
travelplanner/myenv/Lib/site-packages/idna-3.10.dist-info/METADATA
travelplanner/myenv/Lib/site-packages/idna-3.10.dist-info/RECORD
travelplanner/myenv/Lib/site-packages/idna-3.10.dist-info/WHEEL
travelplanner/myenv/Lib/site-packages/jaraco.classes-3.4.0.dist-info/INSTALLER
travelplanner/myenv/Lib/site-packages/jaraco.classes-3.4.0.dist-info/LICENSE
travelplanner/myenv/Lib/site-packages/jaraco.classes-3.4.0.dist-info/METADATA
travelplanner/myenv/Lib/site-packages/jaraco.classes-3.4.0.dist-info/RECORD
travelplanner/myenv/Lib/site-packages/jaraco.classes-3.4.0.dist-info/WHEEL
travelplanner/myenv/Lib/site-packages/jaraco.classes-3.4.0.dist-info/top_level.txt
travelplanner/myenv/Lib/site-packages/jaraco.context-6.0.1.dist-info/INSTALLER
travelplanner/myenv/Lib/site-packages/jaraco.context-6.0.1.dist-info/LICENSE
travelplanner/myenv/Lib/site-packages/jaraco.context-6.0.1.dist-info/METADATA
travelplanner/myenv/Lib/site-packages/jaraco.context-6.0.1.dist-info/RECORD
travelplanner/myenv/Lib/site-packages/jaraco.context-6.0.1.dist-info/WHEEL
