Metadata-Version: 2.4
Name: travelplanner
Version: 0.0.2
Summary: collection of biblical humans and their family relations
Project-URL: Homepage, https://github.com/saikrisnaa/travelplanner
Project-URL: Issues, https://github.com/saikrisnaa/travelplanner
Author-email: sai <yenishettysai@gmail.com>
License-File: LICENSE.txt
Classifier: License :: OSI Approved :: GNU General Public License v3 (GPLv3)
Classifier: Operating System :: OS Independent
Classifier: Programming Language :: Python :: 3
Requires-Python: >=3.0
